LICENSE
asqlite/__init__.py
rapptz_asqlite-1.0.1.dist-info/LICENSE
rapptz_asqlite-1.0.1.dist-info/WHEEL
rapptz_asqlite-1.0.1.dist-info/METADATA
rapptz_asqlite-1.0.1.dist-info/RECORD
