Metadata-Version: 2.1
Name: rapptz-asqlite
Version: 1.0.1
Summary: A simple async wrapper for sqlite3
Home-page: https://github.com/Rapptz/asqlite
License: MIT
Author: Rapptz
Maintainer: Seon82
Requires-Python: >=3.5
Classifier: Intended Audience :: Developers
Classifier: License :: OSI Approved :: MIT License
Classifier: Natural Language :: English
Classifier: Operating System :: OS Independent
Classifier: Programming Language :: Python :: 3
Classifier: Programming Language :: Python :: 3.10
Classifier: Programming Language :: Python :: 3.5
Classifier: Programming Language :: Python :: 3.6
Classifier: Programming Language :: Python :: 3.7
Classifier: Programming Language :: Python :: 3.8
Classifier: Programming Language :: Python :: 3.9
Project-URL: Issue Tracker, https://github.com/Rapptz/asqlite/issues/
Project-URL: Repository, https://github.com/Rapptz/asqlite
